sql_schema/__init__.py
sql_schema/import schema.py
sql_schema/schema.py
sql_schema-0.0.4.dist-info/LICENSE
sql_schema-0.0.4.dist-info/METADATA
sql_schema-0.0.4.dist-info/WHEEL
sql_schema-0.0.4.dist-info/top_level.txt
sql_schema-0.0.4.dist-info/RECORD
