Metadata-Version: 2.1
Name: sql_schema
Version: 0.0.4
Summary: Schema Transfer/Drop Helper
Author: Mohammed Abu Bakkar Kuchikar
Author-email: abu813684@gmail.com
Keywords: python,sql_server,sql,schema,drop,transfer
License-File: LICENSE
Requires-Dist: pypyodbc
